[{"title":"query-string","url":"/library/query-string","id":"query-string"},{"title":"negative-array","url":"/library/negative-array","id":"negative-array"},{"title":"stringify-object","url":"/library/stringify-object","id":"stringify-object"},{"title":"unique-random","url":"/library/unique-random","id":"unique-random"},{"title":"detect-indent","url":"/library/detect-indent","id":"detect-indent"},{"title":"RaptorJS","url":"/library/raptorjs","id":"raptorjs"},{"title":"srcset","url":"/library/srcset","id":"srcset"},{"title":"Polymer","url":"/library/polymer","id":"polymer"},{"title":"devtools-detect","url":"/library/devtools-detect","id":"devtools-detect"},{"title":"ComponentJS","url":"/library/componentjs","id":"componentjs"}]