[{"title":"adam","url":"/library/adam","id":"adam","library":{"id":"adam","description":"Functions to create, process and test objects.","logo":"/images/repo.png","name":"adam","links":{"github":"https://github.com/gamtiq/adam"},"tags":["Object","check","create","field","filter","kind","process","size","split","type","value"]}},{"title":"valuejs","url":"/library/valuejs","id":"valuejs","library":{"id":"valuejs","description":"Provides a Value constructor used to create numbers similar to ranges that can be safely modified within specified boundaries.","logo":"/images/repo.png","name":"valuejs","links":{"github":"https://github.com/karolk/valuejs"},"tags":["max","min","range.","step","value"]}}]